tatools01/ParamsBase.py
tatools01/__init__.py
tatools01/cli.py
tatools01/cli_md2w.py
tatools01/Thoi_gian/taTimers.py
tatools01/md_word/convert_md_to_word.py
tatools01-3.0.7.dist-info/licenses/LICENSE
tatools01-3.0.7.dist-info/METADATA
tatools01-3.0.7.dist-info/WHEEL
tatools01-3.0.7.dist-info/entry_points.txt
tatools01-3.0.7.dist-info/top_level.txt
tatools01-3.0.7.dist-info/RECORD
