Metadata-Version: 2.4
Name: tatools01
Version: 3.0.7
Summary: Thư viện hữu ích của Tuấn Anh.
Home-page: https://pypi.org/project/tatools01/
Author: Tuấn Anh - Foxconn
Author-email: nt.anh.fai@gmail.com
License: MIT
Classifier: Programming Language :: Python :: 3
Classifier: License :: OSI Approved :: MIT License
Classifier: Operating System :: OS Independent
License-File: LICENSE
Requires-Dist: ruamel.yaml
Requires-Dist: python-docx
Requires-Dist: markdown
Requires-Dist: beautifulsoup4
Dynamic: author
Dynamic: author-email
Dynamic: classifier
Dynamic: description
Dynamic: description-content-type
Dynamic: home-page
Dynamic: license
Dynamic: license-file
Dynamic: requires-dist
Dynamic: summary
